{
    "version": "0.4",
    "title": "Block services style 3",
    "type": "section",
    "metadata": {
        "template_type": "section-services",
        "include_in_zip": "1",
        "elementor_pro_required": null,
        "wp_page_template": "elementor_canvas"
    },
    "content": [
        {
            "id": "3d6ebe81",
            "settings": {
                "content_width": {
                    "unit": "px",
                    "size": 1170,
                    "sizes": []
                },
                "structure": "30",
                "background_background": "classic",
                "background_color": "#FFFFFF",
                "margin": {
                    "unit": "px",
                    "top": "0",
                    "right": 0,
                    "bottom": "0",
                    "left": 0,
                    "isLinked": false
                },
                "margin_tablet": {
                    "unit": "px",
                    "top": "0",
                    "right": 0,
                    "bottom": "0",
                    "left": 0,
                    "isLinked": false
                },
                "margin_mobile": {
                    "unit": "px",
                    "top": "0",
                    "right": 0,
                    "bottom": "0",
                    "left": 0,
                    "isLinked": false
                },
                "padding": {
                    "unit": "px",
                    "top": "136",
                    "right": "30",
                    "bottom": "140",
                    "left": "30",
                    "isLinked": false
                },
                "padding_tablet": {
                    "unit": "px",
                    "top": "100",
                    "right": "30",
                    "bottom": "100",
                    "left": "30",
                    "isLinked": false
                },
                "padding_mobile": {
                    "unit": "px",
                    "top": "50",
                    "right": "20",
                    "bottom": "58",
                    "left": "20",
                    "isLinked": false
                }
            },
            "elements": [
                {
                    "id": "18c9fc2a",
                    "settings": {
                        "_column_size": 33,
                        "_inline_size": null,
                        "content_position": "space-between",
                        "space_between_widgets": 0,
                        "margin": {
                            "unit": "px",
                            "top": "0",
                            "right": "20",
                            "bottom": "0",
                            "left": "0",
                            "isLinked": false
                        },
                        "padding": {
                            "unit": "px",
                            "top": "0",
                            "right": "0",
                            "bottom": "0",
                            "left": "0",
                            "isLinked": false
                        },
                        "space_between_widgets_mobile": 0,
                        "margin_mobile": {
                            "unit": "px",
                            "top": "0",
                            "right": "0",
                            "bottom": "0",
                            "left": "0",
                            "isLinked": false
                        },
                        "padding_mobile": {
                            "unit": "px",
                            "top": "0",
                            "right": "0",
                            "bottom": "0",
                            "left": "0",
                            "isLinked": false
                        }
                    },
                    "elements": [
                        {
                            "id": "22aefeb7",
                            "settings": {
                                "layout": "full_width",
                                "margin": {
                                    "unit": "px",
                                    "top": "0",
                                    "right": 0,
                                    "bottom": "0",
                                    "left": 0,
                                    "isLinked": false
                                },
                                "margin_tablet": {
                                    "unit": "px",
                                    "top": "0",
                                    "right": 0,
                                    "bottom": "0",
                                    "left": 0,
                                    "isLinked": false
                                },
                                "padding": {
                                    "unit": "px",
                                    "top": "0",
                                    "right": "100",
                                    "bottom": "0",
                                    "left": "0",
                                    "isLinked": false
                                },
                                "padding_tablet": {
                                    "unit": "px",
                                    "top": "0",
                                    "right": "0",
                                    "bottom": "0",
                                    "left": "0",
                                    "isLinked": false
                                },
                                "margin_mobile": {
                                    "unit": "px",
                                    "top": "0",
                                    "right": 0,
                                    "bottom": "0",
                                    "left": 0,
                                    "isLinked": false
                                },
                                "padding_mobile": {
                                    "unit": "px",
                                    "top": "0",
                                    "right": "0",
                                    "bottom": "0",
                                    "left": "0",
                                    "isLinked": false
                                }
                            },
                            "elements": [
                                {
                                    "id": "a34a47c",
                                    "settings": {
                                        "_column_size": 100,
                                        "_inline_size": null,
                                        "space_between_widgets": 0,
                                        "margin": {
                                            "unit": "px",
                                            "top": "0",
                                            "right": "0",
                                            "bottom": "0",
                                            "left": "0",
                                            "isLinked": false
                                        },
                                        "padding": {
                                            "unit": "px",
                                            "top": "0",
                                            "right": "0",
                                            "bottom": "0",
                                            "left": "0",
                                            "isLinked": false
                                        },
                                        "space_between_widgets_mobile": 0,
                                        "margin_mobile": {
                                            "unit": "px",
                                            "top": "0",
                                            "right": "0",
                                            "bottom": "0",
                                            "left": "0",
                                            "isLinked": false
                                        },
                                        "padding_mobile": {
                                            "unit": "px",
                                            "top": "0",
                                            "right": "0",
                                            "bottom": "0",
                                            "left": "0",
                                            "isLinked": false
                                        },
                                        "content_position": "space-between"
                                    },
                                    "elements": [
                                        {
                                            "id": "1e126d9e",
                                            "settings": {
                                                "image": {
                                                    "url": "http:\/\/template-kit.ancorathemes.com\/drone-photography\/wp-content\/uploads\/sites\/8\/2020\/04\/drone1.png",
                                                    "id": 2403
                                                },
                                                "thumbnail_size": "custom",
                                                "thumbnail_custom_dimension": {
                                                    "width": "128",
                                                    "height": "84"
                                                },
                                                "title_text": "post production",
                                                "description_text": "The best part about Drone Aerial Photography is the new",
                                                "image_space": {
                                                    "unit": "px",
                                                    "size": 12,
                                                    "sizes": []
                                                },
                                                "image_size": {
                                                    "unit": "%",
                                                    "size": 25,
                                                    "sizes": []
                                                },
                                                "image_size_mobile": {
                                                    "unit": "%",
                                                    "size": 20,
                                                    "sizes": []
                                                },
                                                "text_align": "right",
                                                "title_bottom_space": {
                                                    "unit": "px",
                                                    "size": 29,
                                                    "sizes": []
                                                },
                                                "title_bottom_space_tablet": {
                                                    "unit": "px",
                                                    "size": 18,
                                                    "sizes": []
                                                },
                                                "title_bottom_space_mobile": {
                                                    "unit": "px",
                                                    "size": 12,
                                                    "sizes": []
                                                },
                                                "title_color": "#222D35",
                                                "title_typography_typography": "custom",
                                                "title_typography_font_family": "Fjalla One",
                                                "title_typography_font_size": {
                                                    "unit": "rem",
                                                    "size": 1.875,
                                                    "sizes": []
                                                },
                                                "title_typography_font_size_tablet": {
                                                    "unit": "rem",
                                                    "size": 1.5,
                                                    "sizes": []
                                                },
                                                "title_typography_font_weight": "400",
                                                "title_typography_text_transform": "uppercase",
                                                "title_typography_font_style": "normal",
                                                "title_typography_text_decoration": "none",
                                                "title_typography_line_height": {
                                                    "unit": "em",
                                                    "size": 1,
                                                    "sizes": []
                                                },
                                                "title_typography_letter_spacing": {
                                                    "unit": "px",
                                                    "size": 0.6,
                                                    "sizes": []
                                                },
                                                "description_color": "rgba(34, 45, 53, 0.7)",
                                                "description_typography_typography": "custom",
                                                "description_typography_font_size": {
                                                    "unit": "rem",
                                                    "size": 0.875,
                                                    "sizes": []
                                                },
                                                "description_typography_font_size_tablet": {
                                                    "unit": "rem",
                                                    "size": 0.813,
                                                    "sizes": []
                                                },
                                                "description_typography_font_weight": "400",
                                                "description_typography_text_transform": "none",
                                                "description_typography_font_style": "normal",
                                                "description_typography_text_decoration": "none",
                                                "description_typography_line_height": {
                                                    "unit": "em",
                                                    "size": 1.72,
                                                    "sizes": []
                                                },
                                                "description_typography_line_height_tablet": {
                                                    "unit": "em",
                                                    "size": 1.4,
                                                    "sizes": []
                                                },
                                                "description_typography_letter_spacing": {
                                                    "unit": "px",
                                                    "size": -0.15,
                                                    "sizes": []
                                                },
                                                "_margin": {
                                                    "unit": "px",
                                                    "top": "0",
                                                    "right": "0",
                                                    "bottom": "0",
                                                    "left": "0",
                                                    "isLinked": false
                                                },
                                                "_padding": {
                                                    "unit": "px",
                                                    "top": "0",
                                                    "right": "0",
                                                    "bottom": "0",
                                                    "left": "0",
                                                    "isLinked": false
                                                },
                                                "_animation": "fadeInLeft",
                                                "_animation_tablet": "fadeIn"
                                            },
                                            "elements": [],
                                            "isInner": false,
                                            "widgetType": "image-box",
                                            "elType": "widget"
                                        },
                                        {
                                            "id": "2ad0d642",
                                            "settings": {
                                                "icon_list": [
                                                    {
                                                        "text": "Learn More",
                                                        "selected_icon": {
                                                            "value": "",
                                                            "library": ""
                                                        },
                                                        "_id": "c6c6d0a",
                                                        "link": {
                                                            "url": "#",
                                                            "is_external": "",
                                                            "nofollow": "",
                                                            "custom_attributes": ""
                                                        }
                                                    }
                                                ],
                                                "space_between": {
                                                    "unit": "px",
                                                    "size": 0,
                                                    "sizes": []
                                                },
                                                "icon_align": "right",
                                                "icon_size": {
                                                    "unit": "px",
                                                    "size": 0,
                                                    "sizes": []
                                                },
                                                "text_color": "#D72323",
                                                "text_color_hover": "#222D35",
                                                "text_indent": {
                                                    "unit": "px",
                                                    "size": 0,
                                                    "sizes": []
                                                },
                                                "icon_typography_typography": "custom",
                                                "icon_typography_font_family": "Fjalla One",
                                                "icon_typography_font_size": {
                                                    "unit": "rem",
                                                    "size": 1,
                                                    "sizes": []
                                                },
                                                "icon_typography_font_weight": "400",
                                                "icon_typography_text_transform": "uppercase",
                                                "icon_typography_line_height": {
                                                    "unit": "em",
                                                    "size": 1,
                                                    "sizes": []
                                                },
                                                "icon_typography_letter_spacing": {
                                                    "unit": "px",
                                                    "size": 0.96,
                                                    "sizes": []
                                                },
                                                "_margin": {
                                                    "unit": "px",
                                                    "top": "34",
                                                    "right": "0",
                                                    "bottom": "0",
                                                    "left": "0",
                                                    "isLinked": false
                                                },
                                                "_padding": {
                                                    "unit": "px",
                                                    "top": "0",
                                                    "right": "0",
                                                    "bottom": "0",
                                                    "left": "0",
                                                    "isLinked": false
                                                },
                                                "icon_typography_font_size_tablet": {
                                                    "unit": "rem",
                                                    "size": 0.9,
                                                    "sizes": []
                                                },
                                                "_margin_tablet": {
                                                    "unit": "px",
                                                    "top": "20",
                                                    "right": "0",
                                                    "bottom": "0",
                                                    "left": "0",
                                                    "isLinked": false
                                                },
                                                "_margin_mobile": {
                                                    "unit": "px",
                                                    "top": "15",
                                                    "right": "0",
                                                    "bottom": "0",
                                                    "left": "0",
                                                    "isLinked": false
                                                },
                                                "_padding_tablet": {
                                                    "unit": "px",
                                                    "top": "0",
                                                    "right": "0",
                                                    "bottom": "0",
                                                    "left": "0",
                                                    "isLinked": false
                                                },
                                                "_animation": "fadeInLeft",
                                                "_animation_delay": 300,
                                                "_padding_mobile": {
                                                    "unit": "px",
                                                    "top": "0",
                                                    "right": "0",
                                                    "bottom": "0",
                                                    "left": "0",
                                                    "isLinked": false
                                                },
                                                "_animation_tablet": "fadeIn"
                                            },
                                            "elements": [],
                                            "isInner": false,
                                            "widgetType": "icon-list",
                                            "elType": "widget"
                                        }
                                    ],
                                    "isInner": true,
                                    "elType": "column"
                                }
                            ],
                            "isInner": true,
                            "elType": "section"
                        },
                        {
                            "id": "7d52568f",
                            "settings": {
                                "layout": "full_width",
                                "margin": {
                                    "unit": "px",
                                    "top": "26",
                                    "right": 0,
                                    "bottom": "0",
                                    "left": 0,
                                    "isLinked": false
                                },
                                "margin_tablet": {
                                    "unit": "px",
                                    "top": "30",
                                    "right": 0,
                                    "bottom": "0",
                                    "left": 0,
                                    "isLinked": false
                                },
                                "padding": {
                                    "unit": "px",
                                    "top": "0",
                                    "right": "100",
                                    "bottom": "0",
                                    "left": "0",
                                    "isLinked": false
                                },
                                "padding_tablet": {
                                    "unit": "px",
                                    "top": "0",
                                    "right": "0",
                                    "bottom": "0",
                                    "left": "0",
                                    "isLinked": false
                                },
                                "margin_mobile": {
                                    "unit": "px",
                                    "top": "25",
                                    "right": 0,
                                    "bottom": "0",
                                    "left": 0,
                                    "isLinked": false
                                },
                                "padding_mobile": {
                                    "unit": "px",
                                    "top": "0",
                                    "right": "0",
                                    "bottom": "0",
                                    "left": "0",
                                    "isLinked": false
                                }
                            },
                            "elements": [
                                {
                                    "id": "2df31050",
                                    "settings": {
                                        "_column_size": 100,
                                        "_inline_size": null,
                                        "space_between_widgets": 0,
                                        "margin": {
                                            "unit": "px",
                                            "top": "0",
                                            "right": "0",
                                            "bottom": "0",
                                            "left": "0",
                                            "isLinked": false
                                        },
                                        "padding": {
                                            "unit": "px",
                                            "top": "0",
                                            "right": "0",
                                            "bottom": "0",
                                            "left": "0",
                                            "isLinked": false
                                        },
                                        "space_between_widgets_mobile": 0,
                                        "margin_mobile": {
                                            "unit": "px",
                                            "top": "0",
                                            "right": "0",
                                            "bottom": "0",
                                            "left": "0",
                                            "isLinked": false
                                        },
                                        "padding_mobile": {
                                            "unit": "px",
                                            "top": "0",
                                            "right": "0",
                                            "bottom": "0",
                                            "left": "0",
                                            "isLinked": false
                                        }
                                    },
                                    "elements": [
                                        {
                                            "id": "1a43f67e",
                                            "settings": {
                                                "image": {
                                                    "url": "http:\/\/template-kit.ancorathemes.com\/drone-photography\/wp-content\/uploads\/sites\/8\/2020\/04\/drone2.png",
                                                    "id": 2404
                                                },
                                                "thumbnail_size": "custom",
                                                "thumbnail_custom_dimension": {
                                                    "width": "104",
                                                    "height": "88"
                                                },
                                                "title_text": "4k video",
                                                "description_text": "What is 4K? Well, I\u2019ll tell you what it isn\u2019t 4K is not standard definition.",
                                                "image_size": {
                                                    "unit": "%",
                                                    "size": 19,
                                                    "sizes": []
                                                },
                                                "image_size_mobile": {
                                                    "unit": "%",
                                                    "size": 17,
                                                    "sizes": []
                                                },
                                                "text_align": "right",
                                                "title_bottom_space": {
                                                    "unit": "px",
                                                    "size": 29,
                                                    "sizes": []
                                                },
                                                "title_bottom_space_tablet": {
                                                    "unit": "px",
                                                    "size": 18,
                                                    "sizes": []
                                                },
                                                "title_bottom_space_mobile": {
                                                    "unit": "px",
                                                    "size": 12,
                                                    "sizes": []
                                                },
                                                "title_color": "#222D35",
                                                "title_typography_typography": "custom",
                                                "title_typography_font_family": "Fjalla One",
                                                "title_typography_font_size": {
                                                    "unit": "rem",
                                                    "size": 1.875,
                                                    "sizes": []
                                                },
                                                "title_typography_font_size_tablet": {
                                                    "unit": "rem",
                                                    "size": 1.5,
                                                    "sizes": []
                                                },
                                                "title_typography_font_weight": "400",
                                                "title_typography_text_transform": "uppercase",
                                                "title_typography_font_style": "normal",
                                                "title_typography_text_decoration": "none",
                                                "title_typography_line_height": {
                                                    "unit": "em",
                                                    "size": 1,
                                                    "sizes": []
                                                },
                                                "title_typography_letter_spacing": {
                                                    "unit": "px",
                                                    "size": 0.6,
                                                    "sizes": []
                                                },
                                                "description_color": "rgba(34, 45, 53, 0.7)",
                                                "description_typography_typography": "custom",
                                                "description_typography_font_size": {
                                                    "unit": "rem",
                                                    "size": 0.875,
                                                    "sizes": []
                                                },
                                                "description_typography_font_size_tablet": {
                                                    "unit": "rem",
                                                    "size": 0.813,
                                                    "sizes": []
                                                },
                                                "description_typography_font_weight": "400",
                                                "description_typography_text_transform": "none",
                                                "description_typography_font_style": "normal",
                                                "description_typography_text_decoration": "none",
                                                "description_typography_line_height": {
                                                    "unit": "em",
                                                    "size": 1.72,
                                                    "sizes": []
                                                },
                                                "description_typography_line_height_tablet": {
                                                    "unit": "em",
                                                    "size": 1.4,
                                                    "sizes": []
                                                },
                                                "description_typography_letter_spacing": {
                                                    "unit": "px",
                                                    "size": -0.15,
                                                    "sizes": []
                                                },
                                                "_margin": {
                                                    "unit": "px",
                                                    "top": "0",
                                                    "right": "0",
                                                    "bottom": "0",
                                                    "left": "0",
                                                    "isLinked": false
                                                },
                                                "_padding": {
                                                    "unit": "px",
                                                    "top": "0",
                                                    "right": "0",
                                                    "bottom": "0",
                                                    "left": "0",
                                                    "isLinked": false
                                                },
                                                "_animation": "fadeInLeft",
                                                "_animation_tablet": "fadeIn"
                                            },
                                            "elements": [],
                                            "isInner": false,
                                            "widgetType": "image-box",
                                            "elType": "widget"
                                        },
                                        {
                                            "id": "7707d789",
                                            "settings": {
                                                "icon_list": [
                                                    {
                                                        "text": "Learn More",
                                                        "selected_icon": {
                                                            "value": "",
                                                            "library": ""
                                                        },
                                                        "_id": "c6c6d0a",
                                                        "link": {
                                                            "url": "#",
                                                            "is_external": "",
                                                            "nofollow": "",
                                                            "custom_attributes": ""
                                                        }
                                                    }
                                                ],
                                                "space_between": {
                                                    "unit": "px",
                                                    "size": 0,
                                                    "sizes": []
                                                },
                                                "icon_align": "right",
                                                "icon_size": {
                                                    "unit": "px",
                                                    "size": 0,
                                                    "sizes": []
                                                },
                                                "text_color": "#D72323",
                                                "text_color_hover": "#222D35",
                                                "text_indent": {
                                                    "unit": "px",
                                                    "size": 0,
                                                    "sizes": []
                                                },
                                                "icon_typography_typography": "custom",
                                                "icon_typography_font_family": "Fjalla One",
                                                "icon_typography_font_size": {
                                                    "unit": "rem",
                                                    "size": 1,
                                                    "sizes": []
                                                },
                                                "icon_typography_font_weight": "400",
                                                "icon_typography_text_transform": "uppercase",
                                                "icon_typography_line_height": {
                                                    "unit": "em",
                                                    "size": 1,
                                                    "sizes": []
                                                },
                                                "icon_typography_letter_spacing": {
                                                    "unit": "px",
                                                    "size": 0.96,
                                                    "sizes": []
                                                },
                                                "_margin": {
                                                    "unit": "px",
                                                    "top": "34",
                                                    "right": "0",
                                                    "bottom": "0",
                                                    "left": "0",
                                                    "isLinked": false
                                                },
                                                "_padding": {
                                                    "unit": "px",
                                                    "top": "0",
                                                    "right": "0",
                                                    "bottom": "0",
                                                    "left": "0",
                                                    "isLinked": false
                                                },
                                                "icon_typography_font_size_tablet": {
                                                    "unit": "rem",
                                                    "size": 0.9,
                                                    "sizes": []
                                                },
                                                "_margin_tablet": {
                                                    "unit": "px",
                                                    "top": "20",
                                                    "right": "0",
                                                    "bottom": "0",
                                                    "left": "0",
                                                    "isLinked": false
                                                },
                                                "_margin_mobile": {
                                                    "unit": "px",
                                                    "top": "15",
                                                    "right": "0",
                                                    "bottom": "0",
                                                    "left": "0",
                                                    "isLinked": false
                                                },
                                                "_padding_tablet": {
                                                    "unit": "px",
                                                    "top": "0",
                                                    "right": "0",
                                                    "bottom": "0",
                                                    "left": "0",
                                                    "isLinked": false
                                                },
                                                "_animation": "fadeInLeft",
                                                "_animation_delay": 100,
                                                "_padding_mobile": {
                                                    "unit": "px",
                                                    "top": "0",
                                                    "right": "0",
                                                    "bottom": "0",
                                                    "left": "0",
                                                    "isLinked": false
                                                },
                                                "_animation_tablet": "fadeIn"
                                            },
                                            "elements": [],
                                            "isInner": false,
                                            "widgetType": "icon-list",
                                            "elType": "widget"
                                        }
                                    ],
                                    "isInner": true,
                                    "elType": "column"
                                }
                            ],
                            "isInner": true,
                            "elType": "section"
                        }
                    ],
                    "isInner": false,
                    "elType": "column"
                },
                {
                    "id": "3c8272e8",
                    "settings": {
                        "_column_size": 33,
                        "_inline_size": null,
                        "space_between_widgets": 0,
                        "margin": {
                            "unit": "px",
                            "top": "0",
                            "right": "10",
                            "bottom": "0",
                            "left": "10",
                            "isLinked": false
                        },
                        "margin_tablet": {
                            "unit": "px",
                            "top": "0",
                            "right": "10",
                            "bottom": "0",
                            "left": "10",
                            "isLinked": false
                        },
                        "padding": {
                            "unit": "px",
                            "top": "0",
                            "right": "0",
                            "bottom": "0",
                            "left": "0",
                            "isLinked": false
                        },
                        "space_between_widgets_mobile": 0,
                        "margin_mobile": {
                            "unit": "px",
                            "top": "28",
                            "right": "0",
                            "bottom": "0",
                            "left": "0",
                            "isLinked": false
                        },
                        "padding_mobile": {
                            "unit": "px",
                            "top": "0",
                            "right": "0",
                            "bottom": "0",
                            "left": "0",
                            "isLinked": false
                        }
                    },
                    "elements": [
                        {
                            "id": "596f6ae7",
                            "settings": {
                                "space": {
                                    "unit": "px",
                                    "size": 508,
                                    "sizes": []
                                },
                                "space_tablet": {
                                    "unit": "px",
                                    "size": 430,
                                    "sizes": []
                                },
                                "_margin": {
                                    "unit": "px",
                                    "top": "0",
                                    "right": "0",
                                    "bottom": "0",
                                    "left": "0",
                                    "isLinked": false
                                },
                                "_padding": {
                                    "unit": "px",
                                    "top": "0",
                                    "right": "0",
                                    "bottom": "0",
                                    "left": "0",
                                    "isLinked": false
                                },
                                "_background_background": "classic",
                                "_background_image": {
                                    "url": "http:\/\/template-kit.ancorathemes.com\/drone-photography\/wp-content\/uploads\/sites\/8\/2020\/04\/drone-in-flight-with-cloudy-sky-PTCUKNJ-scaled.jpg",
                                    "id": 26
                                },
                                "_background_position": "center center",
                                "_background_repeat": "no-repeat",
                                "_background_size": "cover",
                                "space_mobile": {
                                    "unit": "px",
                                    "size": 350,
                                    "sizes": []
                                },
                                "_animation": "fadeInUp",
                                "_animation_tablet": "fadeIn",
                                "animation_duration": "fast"
                            },
                            "elements": [],
                            "isInner": false,
                            "widgetType": "spacer",
                            "elType": "widget"
                        }
                    ],
                    "isInner": false,
                    "elType": "column"
                },
                {
                    "id": "389379af",
                    "settings": {
                        "_column_size": 33,
                        "_inline_size": null,
                        "content_position": "space-between",
                        "space_between_widgets": 0,
                        "margin": {
                            "unit": "px",
                            "top": "0",
                            "right": "0",
                            "bottom": "0",
                            "left": "20",
                            "isLinked": false
                        },
                        "padding": {
                            "unit": "px",
                            "top": "0",
                            "right": "0",
                            "bottom": "0",
                            "left": "0",
                            "isLinked": false
                        },
                        "space_between_widgets_mobile": 0,
                        "margin_mobile": {
                            "unit": "px",
                            "top": "26",
                            "right": "0",
                            "bottom": "0",
                            "left": "0",
                            "isLinked": false
                        },
                        "padding_mobile": {
                            "unit": "px",
                            "top": "0",
                            "right": "0",
                            "bottom": "0",
                            "left": "0",
                            "isLinked": false
                        }
                    },
                    "elements": [
                        {
                            "id": "7fdcb06d",
                            "settings": {
                                "layout": "full_width",
                                "margin": {
                                    "unit": "px",
                                    "top": "0",
                                    "right": 0,
                                    "bottom": "0",
                                    "left": 0,
                                    "isLinked": false
                                },
                                "margin_tablet": {
                                    "unit": "px",
                                    "top": "0",
                                    "right": 0,
                                    "bottom": "0",
                                    "left": 0,
                                    "isLinked": false
                                },
                                "padding": {
                                    "unit": "px",
                                    "top": "0",
                                    "right": "0",
                                    "bottom": "0",
                                    "left": "100",
                                    "isLinked": false
                                },
                                "padding_tablet": {
                                    "unit": "px",
                                    "top": "0",
                                    "right": "0",
                                    "bottom": "0",
                                    "left": "0",
                                    "isLinked": false
                                },
                                "margin_mobile": {
                                    "unit": "px",
                                    "top": "0",
                                    "right": 0,
                                    "bottom": "0",
                                    "left": 0,
                                    "isLinked": false
                                },
                                "padding_mobile": {
                                    "unit": "px",
                                    "top": "0",
                                    "right": "0",
                                    "bottom": "0",
                                    "left": "0",
                                    "isLinked": false
                                }
                            },
                            "elements": [
                                {
                                    "id": "42059c55",
                                    "settings": {
                                        "_column_size": 100,
                                        "_inline_size": null,
                                        "space_between_widgets": 0,
                                        "margin": {
                                            "unit": "px",
                                            "top": "0",
                                            "right": "0",
                                            "bottom": "0",
                                            "left": "0",
                                            "isLinked": false
                                        },
                                        "padding": {
                                            "unit": "px",
                                            "top": "0",
                                            "right": "0",
                                            "bottom": "0",
                                            "left": "0",
                                            "isLinked": false
                                        },
                                        "space_between_widgets_mobile": 0,
                                        "margin_mobile": {
                                            "unit": "px",
                                            "top": "0",
                                            "right": "0",
                                            "bottom": "0",
                                            "left": "0",
                                            "isLinked": false
                                        },
                                        "padding_mobile": {
                                            "unit": "px",
                                            "top": "0",
                                            "right": "0",
                                            "bottom": "0",
                                            "left": "0",
                                            "isLinked": false
                                        }
                                    },
                                    "elements": [
                                        {
                                            "id": "1139787f",
                                            "settings": {
                                                "image": {
                                                    "url": "http:\/\/template-kit.ancorathemes.com\/drone-photography\/wp-content\/uploads\/sites\/8\/2020\/04\/drone@2x.png",
                                                    "id": 2448
                                                },
                                                "thumbnail_size": "custom",
                                                "thumbnail_custom_dimension": {
                                                    "width": "119",
                                                    "height": "99"
                                                },
                                                "title_text": "Customization",
                                                "description_text": "Here at Drone Media, we pride \nourselves in our ability to meet your \n",
                                                "image_space": {
                                                    "unit": "px",
                                                    "size": 9,
                                                    "sizes": []
                                                },
                                                "image_size": {
                                                    "unit": "%",
                                                    "size": 21,
                                                    "sizes": []
                                                },
                                                "image_size_tablet": {
                                                    "unit": "%",
                                                    "size": 18,
                                                    "sizes": []
                                                },
                                                "image_size_mobile": {
                                                    "unit": "%",
                                                    "size": 17,
                                                    "sizes": []
                                                },
                                                "text_align": "left",
                                                "title_bottom_space": {
                                                    "unit": "px",
                                                    "size": 29,
                                                    "sizes": []
                                                },
                                                "title_bottom_space_tablet": {
                                                    "unit": "px",
                                                    "size": 18,
                                                    "sizes": []
                                                },
                                                "title_bottom_space_mobile": {
                                                    "unit": "px",
                                                    "size": 12,
                                                    "sizes": []
                                                },
                                                "title_color": "#222D35",
                                                "title_typography_typography": "custom",
                                                "title_typography_font_family": "Fjalla One",
                                                "title_typography_font_size": {
                                                    "unit": "rem",
                                                    "size": 1.875,
                                                    "sizes": []
                                                },
                                                "title_typography_font_size_tablet": {
                                                    "unit": "rem",
                                                    "size": 1.5,
                                                    "sizes": []
                                                },
                                                "title_typography_font_weight": "400",
                                                "title_typography_text_transform": "uppercase",
                                                "title_typography_font_style": "normal",
                                                "title_typography_text_decoration": "none",
                                                "title_typography_line_height": {
                                                    "unit": "em",
                                                    "size": 1,
                                                    "sizes": []
                                                },
                                                "title_typography_letter_spacing": {
                                                    "unit": "px",
                                                    "size": 0.6,
                                                    "sizes": []
                                                },
                                                "description_color": "rgba(34, 45, 53, 0.7)",
                                                "description_typography_typography": "custom",
                                                "description_typography_font_size": {
                                                    "unit": "rem",
                                                    "size": 0.875,
                                                    "sizes": []
                                                },
                                                "description_typography_font_size_tablet": {
                                                    "unit": "rem",
                                                    "size": 0.813,
                                                    "sizes": []
                                                },
                                                "description_typography_font_weight": "400",
                                                "description_typography_text_transform": "none",
                                                "description_typography_font_style": "normal",
                                                "description_typography_text_decoration": "none",
                                                "description_typography_line_height": {
                                                    "unit": "em",
                                                    "size": 1.72,
                                                    "sizes": []
                                                },
                                                "description_typography_line_height_tablet": {
                                                    "unit": "em",
                                                    "size": 1.4,
                                                    "sizes": []
                                                },
                                                "description_typography_letter_spacing": {
                                                    "unit": "px",
                                                    "size": -0.15,
                                                    "sizes": []
                                                },
                                                "_margin": {
                                                    "unit": "px",
                                                    "top": "0",
                                                    "right": "0",
                                                    "bottom": "0",
                                                    "left": "0",
                                                    "isLinked": false
                                                },
                                                "_margin_tablet": {
                                                    "unit": "px",
                                                    "top": "0",
                                                    "right": "0",
                                                    "bottom": "0",
                                                    "left": "0",
                                                    "isLinked": false
                                                },
                                                "_padding": {
                                                    "unit": "px",
                                                    "top": "0",
                                                    "right": "0",
                                                    "bottom": "0",
                                                    "left": "0",
                                                    "isLinked": false
                                                },
                                                "_padding_tablet": {
                                                    "unit": "px",
                                                    "top": "0",
                                                    "right": "0",
                                                    "bottom": "0",
                                                    "left": "0",
                                                    "isLinked": false
                                                },
                                                "_animation": "fadeInRight",
                                                "_animation_tablet": "fadeIn"
                                            },
                                            "elements": [],
                                            "isInner": false,
                                            "widgetType": "image-box",
                                            "elType": "widget"
                                        },
                                        {
                                            "id": "db76895",
                                            "settings": {
                                                "icon_list": [
                                                    {
                                                        "text": "Learn More",
                                                        "selected_icon": {
                                                            "value": "",
                                                            "library": ""
                                                        },
                                                        "_id": "c6c6d0a",
                                                        "link": {
                                                            "url": "#",
                                                            "is_external": "",
                                                            "nofollow": "",
                                                            "custom_attributes": ""
                                                        }
                                                    }
                                                ],
                                                "space_between": {
                                                    "unit": "px",
                                                    "size": 0,
                                                    "sizes": []
                                                },
                                                "icon_align": "left",
                                                "icon_size": {
                                                    "unit": "px",
                                                    "size": 0,
                                                    "sizes": []
                                                },
                                                "text_color": "#D72323",
                                                "text_color_hover": "#222D35",
                                                "text_indent": {
                                                    "unit": "px",
                                                    "size": 0,
                                                    "sizes": []
                                                },
                                                "icon_typography_typography": "custom",
                                                "icon_typography_font_family": "Fjalla One",
                                                "icon_typography_font_size": {
                                                    "unit": "rem",
                                                    "size": 1,
                                                    "sizes": []
                                                },
                                                "icon_typography_font_weight": "400",
                                                "icon_typography_text_transform": "uppercase",
                                                "icon_typography_line_height": {
                                                    "unit": "em",
                                                    "size": 1,
                                                    "sizes": []
                                                },
                                                "icon_typography_letter_spacing": {
                                                    "unit": "px",
                                                    "size": 0.96,
                                                    "sizes": []
                                                },
                                                "_margin": {
                                                    "unit": "px",
                                                    "top": "34",
                                                    "right": "0",
                                                    "bottom": "0",
                                                    "left": "0",
                                                    "isLinked": false
                                                },
                                                "_padding": {
                                                    "unit": "px",
                                                    "top": "0",
                                                    "right": "0",
                                                    "bottom": "0",
                                                    "left": "0",
                                                    "isLinked": false
                                                },
                                                "icon_typography_font_size_tablet": {
                                                    "unit": "rem",
                                                    "size": 0.9,
                                                    "sizes": []
                                                },
                                                "_margin_tablet": {
                                                    "unit": "px",
                                                    "top": "20",
                                                    "right": "0",
                                                    "bottom": "0",
                                                    "left": "0",
                                                    "isLinked": false
                                                },
                                                "_margin_mobile": {
                                                    "unit": "px",
                                                    "top": "15",
                                                    "right": "0",
                                                    "bottom": "0",
                                                    "left": "0",
                                                    "isLinked": false
                                                },
                                                "_padding_tablet": {
                                                    "unit": "px",
                                                    "top": "0",
                                                    "right": "0",
                                                    "bottom": "0",
                                                    "left": "0",
                                                    "isLinked": false
                                                },
                                                "_animation": "fadeInRight",
                                                "_animation_delay": 100,
                                                "_padding_mobile": {
                                                    "unit": "px",
                                                    "top": "0",
                                                    "right": "0",
                                                    "bottom": "0",
                                                    "left": "0",
                                                    "isLinked": false
                                                },
                                                "icon_self_align": "left",
                                                "_animation_tablet": "fadeIn"
                                            },
                                            "elements": [],
                                            "isInner": false,
                                            "widgetType": "icon-list",
                                            "elType": "widget"
                                        }
                                    ],
                                    "isInner": true,
                                    "elType": "column"
                                }
                            ],
                            "isInner": true,
                            "elType": "section"
                        },
                        {
                            "id": "775f165f",
                            "settings": {
                                "layout": "full_width",
                                "margin": {
                                    "unit": "px",
                                    "top": "26",
                                    "right": 0,
                                    "bottom": "0",
                                    "left": 0,
                                    "isLinked": false
                                },
                                "margin_tablet": {
                                    "unit": "px",
                                    "top": "30",
                                    "right": 0,
                                    "bottom": "0",
                                    "left": 0,
                                    "isLinked": false
                                },
                                "padding": {
                                    "unit": "px",
                                    "top": "0",
                                    "right": "0",
                                    "bottom": "0",
                                    "left": "100",
                                    "isLinked": false
                                },
                                "padding_tablet": {
                                    "unit": "px",
                                    "top": "0",
                                    "right": "0",
                                    "bottom": "0",
                                    "left": "0",
                                    "isLinked": false
                                },
                                "margin_mobile": {
                                    "unit": "px",
                                    "top": "26",
                                    "right": 0,
                                    "bottom": "0",
                                    "left": 0,
                                    "isLinked": false
                                },
                                "padding_mobile": {
                                    "unit": "px",
                                    "top": "0",
                                    "right": "0",
                                    "bottom": "0",
                                    "left": "0",
                                    "isLinked": false
                                }
                            },
                            "elements": [
                                {
                                    "id": "7357f1f7",
                                    "settings": {
                                        "_column_size": 100,
                                        "_inline_size": null,
                                        "space_between_widgets": 0,
                                        "margin": {
                                            "unit": "px",
                                            "top": "0",
                                            "right": "0",
                                            "bottom": "0",
                                            "left": "0",
                                            "isLinked": false
                                        },
                                        "padding": {
                                            "unit": "px",
                                            "top": "0",
                                            "right": "0",
                                            "bottom": "0",
                                            "left": "0",
                                            "isLinked": false
                                        }
                                    },
                                    "elements": [
                                        {
                                            "id": "faa8c79",
                                            "settings": {
                                                "image": {
                                                    "url": "http:\/\/template-kit.ancorathemes.com\/drone-photography\/wp-content\/uploads\/sites\/8\/2020\/04\/drone3.png",
                                                    "id": 2405
                                                },
                                                "thumbnail_size": "custom",
                                                "thumbnail_custom_dimension": {
                                                    "width": "100",
                                                    "height": "100"
                                                },
                                                "title_text": "Edition",
                                                "description_text": "Here at Drone Media, we pride \nourselves in our ability to meet your \n",
                                                "image_space": {
                                                    "unit": "px",
                                                    "size": 7,
                                                    "sizes": []
                                                },
                                                "image_size": {
                                                    "unit": "%",
                                                    "size": 18,
                                                    "sizes": []
                                                },
                                                "image_size_mobile": {
                                                    "unit": "%",
                                                    "size": 15,
                                                    "sizes": []
                                                },
                                                "text_align": "left",
                                                "title_bottom_space": {
                                                    "unit": "px",
                                                    "size": 29,
                                                    "sizes": []
                                                },
                                                "title_bottom_space_tablet": {
                                                    "unit": "px",
                                                    "size": 18,
                                                    "sizes": []
                                                },
                                                "title_bottom_space_mobile": {
                                                    "unit": "px",
                                                    "size": 12,
                                                    "sizes": []
                                                },
                                                "title_color": "#222D35",
                                                "title_typography_typography": "custom",
                                                "title_typography_font_family": "Fjalla One",
                                                "title_typography_font_size": {
                                                    "unit": "rem",
                                                    "size": 1.875,
                                                    "sizes": []
                                                },
                                                "title_typography_font_size_tablet": {
                                                    "unit": "rem",
                                                    "size": 1.5,
                                                    "sizes": []
                                                },
                                                "title_typography_font_weight": "400",
                                                "title_typography_text_transform": "uppercase",
                                                "title_typography_font_style": "normal",
                                                "title_typography_text_decoration": "none",
                                                "title_typography_line_height": {
                                                    "unit": "em",
                                                    "size": 1,
                                                    "sizes": []
                                                },
                                                "title_typography_letter_spacing": {
                                                    "unit": "px",
                                                    "size": 0.6,
                                                    "sizes": []
                                                },
                                                "description_color": "rgba(34, 45, 53, 0.7)",
                                                "description_typography_typography": "custom",
                                                "description_typography_font_size": {
                                                    "unit": "rem",
                                                    "size": 0.875,
                                                    "sizes": []
                                                },
                                                "description_typography_font_size_tablet": {
                                                    "unit": "rem",
                                                    "size": 0.813,
                                                    "sizes": []
                                                },
                                                "description_typography_font_weight": "400",
                                                "description_typography_text_transform": "none",
                                                "description_typography_font_style": "normal",
                                                "description_typography_text_decoration": "none",
                                                "description_typography_line_height": {
                                                    "unit": "em",
                                                    "size": 1.72,
                                                    "sizes": []
                                                },
                                                "description_typography_line_height_tablet": {
                                                    "unit": "em",
                                                    "size": 1.4,
                                                    "sizes": []
                                                },
                                                "description_typography_letter_spacing": {
                                                    "unit": "px",
                                                    "size": -0.15,
                                                    "sizes": []
                                                },
                                                "_margin": {
                                                    "unit": "px",
                                                    "top": "0",
                                                    "right": "0",
                                                    "bottom": "0",
                                                    "left": "0",
                                                    "isLinked": false
                                                },
                                                "_padding": {
                                                    "unit": "px",
                                                    "top": "0",
                                                    "right": "0",
                                                    "bottom": "0",
                                                    "left": "0",
                                                    "isLinked": false
                                                },
                                                "_animation": "fadeInRight",
                                                "_animation_tablet": "fadeIn"
                                            },
                                            "elements": [],
                                            "isInner": false,
                                            "widgetType": "image-box",
                                            "elType": "widget"
                                        },
                                        {
                                            "id": "2a0e2342",
                                            "settings": {
                                                "icon_list": [
                                                    {
                                                        "text": "Learn More",
                                                        "selected_icon": {
                                                            "value": "",
                                                            "library": ""
                                                        },
                                                        "_id": "c6c6d0a",
                                                        "link": {
                                                            "url": "#",
                                                            "is_external": "",
                                                            "nofollow": "",
                                                            "custom_attributes": ""
                                                        }
                                                    }
                                                ],
                                                "space_between": {
                                                    "unit": "px",
                                                    "size": 0,
                                                    "sizes": []
                                                },
                                                "icon_align": "left",
                                                "icon_size": {
                                                    "unit": "px",
                                                    "size": 0,
                                                    "sizes": []
                                                },
                                                "text_color": "#D72323",
                                                "text_color_hover": "#222D35",
                                                "text_indent": {
                                                    "unit": "px",
                                                    "size": 0,
                                                    "sizes": []
                                                },
                                                "icon_typography_typography": "custom",
                                                "icon_typography_font_family": "Fjalla One",
                                                "icon_typography_font_size": {
                                                    "unit": "rem",
                                                    "size": 1,
                                                    "sizes": []
                                                },
                                                "icon_typography_font_weight": "400",
                                                "icon_typography_text_transform": "uppercase",
                                                "icon_typography_line_height": {
                                                    "unit": "em",
                                                    "size": 1,
                                                    "sizes": []
                                                },
                                                "icon_typography_letter_spacing": {
                                                    "unit": "px",
                                                    "size": 0.96,
                                                    "sizes": []
                                                },
                                                "_margin": {
                                                    "unit": "px",
                                                    "top": "34",
                                                    "right": "0",
                                                    "bottom": "0",
                                                    "left": "0",
                                                    "isLinked": false
                                                },
                                                "_padding": {
                                                    "unit": "px",
                                                    "top": "0",
                                                    "right": "0",
                                                    "bottom": "0",
                                                    "left": "0",
                                                    "isLinked": false
                                                },
                                                "icon_typography_font_size_tablet": {
                                                    "unit": "rem",
                                                    "size": 0.9,
                                                    "sizes": []
                                                },
                                                "_margin_tablet": {
                                                    "unit": "px",
                                                    "top": "20",
                                                    "right": "0",
                                                    "bottom": "0",
                                                    "left": "0",
                                                    "isLinked": false
                                                },
                                                "_margin_mobile": {
                                                    "unit": "px",
                                                    "top": "15",
                                                    "right": "0",
                                                    "bottom": "0",
                                                    "left": "0",
                                                    "isLinked": false
                                                },
                                                "_padding_tablet": {
                                                    "unit": "px",
                                                    "top": "0",
                                                    "right": "0",
                                                    "bottom": "0",
                                                    "left": "0",
                                                    "isLinked": false
                                                },
                                                "_animation": "fadeInRight",
                                                "_animation_delay": 100,
                                                "_padding_mobile": {
                                                    "unit": "px",
                                                    "top": "0",
                                                    "right": "0",
                                                    "bottom": "0",
                                                    "left": "0",
                                                    "isLinked": false
                                                },
                                                "icon_self_align": "left",
                                                "_animation_tablet": "fadeIn"
                                            },
                                            "elements": [],
                                            "isInner": false,
                                            "widgetType": "icon-list",
                                            "elType": "widget"
                                        }
                                    ],
                                    "isInner": true,
                                    "elType": "column"
                                }
                            ],
                            "isInner": true,
                            "elType": "section"
                        }
                    ],
                    "isInner": false,
                    "elType": "column"
                }
            ],
            "isInner": false,
            "elType": "section"
        }
    ]
}